[
  {
    "framename": "amba",
    "sound1": "e1/m_inmateramba.wav",
    "frame1": 1,
    "sound2": "",
    "frame2": "",
    "flag": "FRAME_LOOP",
    "attack seq 1": "",
    "attack seq 2": "",
    "anim speed": "",
    "anim %": "",
    "sound2 %": ""
  },
  {
    "framename": "ataka",
    "sound1": "e1/m_inmaterataka.wav",
    "frame1": 0,
    "sound2": "",
    "frame2": "",
    "flag": "FRAME_ONCE",
    "attack seq 1": 1,
    "attack seq 2": "",
    "anim speed": 120,
    "anim %": "",
    "sound2 %": ""
  },
  {
    "framename": "atakb",
    "sound1": "e1/m_inmateratakc.wav",
    "frame1": 3,
    "sound2": "global/m_knifehite.wav",
    "frame2": "",
    "flag": "FRAME_ONCE",
    "attack seq 1": 10,
    "attack seq 2": "",
    "anim speed": 120,
    "anim %": "",
    "sound2 %": ""
  },
  {
    "framename": "atakc",
    "sound1": "e1/m_inmateratakb.wav",
    "frame1": 1,
    "sound2": "",
    "frame2": "",
    "flag": "FRAME_ONCE",
    "attack seq 1": 1,
    "attack seq 2": "",
    "anim speed": 120,
    "anim %": "",
    "sound2 %": ""
  },
  {
    "framename": "atakstart",
    "sound1": "e1/m_inmaterruna.wav",
    "frame1": 3,
    "sound2": "e1/m_inmaterruna.wav",
    "frame2": 11,
    "flag": "FRAME_ONCE",
    "attack seq 1": "",
    "attack seq 2": "",
    "anim speed": "",
    "anim %": "",
    "sound2 %": ""
  },
  {
    "framename": "atakstop",
    "sound1": "e1/m_inmaterruna.wav",
    "frame1": 8,
    "sound2": "e1/m_inmaterruna.wav",
    "frame2": 16,
    "flag": "FRAME_ONCE",
    "attack seq 1": "",
    "attack seq 2": "",
    "anim speed": "",
    "anim %": "",
    "sound2 %": ""
  },
  {
    "framename": "hita",
    "sound1": "e1/m_inmaterha.wav",
    "frame1": 1,
    "sound2": "",
    "frame2": "",
    "flag": "FRAME_ONCE",
    "attack seq 1": "",
    "attack seq 2": "",
    "anim speed": "",
    "anim %": "",
    "sound2 %": ""
  },
  {
    "framename": "diea",
    "sound1": "e1/m_inmaterdiea.wav",
    "frame1": 1,
    "sound2": "",
    "frame2": "",
    "flag": "FRAME_ONCE",
    "attack seq 1": "",
    "attack seq 2": "",
    "anim speed": "",
    "anim %": "",
    "sound2 %": ""
  },
  {
    "framename": "runa",
    "sound1": "e1/m_inmaterruna.wav",
    "frame1": 1,
    "sound2": "e1/m_inmaterruna.wav",
    "frame2": 12,
    "flag": "FRAME_ONCE",
    "attack seq 1": "",
    "attack seq 2": "",
    "anim speed": 120,
    "anim %": "",
    "sound2 %": ""
  },
  {
    "framename": "walka",
    "sound1": "e1/m_inmaterwalka.wav",
    "frame1": 1,
    "sound2": "e1/m_inmaterwalka.wav",
    "frame2": 15,
    "flag": "FRAME_ONCE",
    "attack seq 1": "",
    "attack seq 2": "",
    "anim speed": 45,
    "anim %": "",
    "sound2 %": ""
  },
  {
    "framename": "sight",
    "sound1": "e1/m_inmatersight.wav",
    "frame1": 1,
    "sound2": "",
    "frame2": "",
    "flag": "FRAME_ONCE",
    "attack seq 1": "",
    "attack seq 2": "",
    "anim speed": "",
    "anim %": "",
    "sound2 %": ""
  }
]
